{
  "destinationName": "Kalsubai",
  "destinationSlug": "kalsubai",
  "departureCity": "MUMBAI",
  "routePath": "/treks/kalsubai/mumbai",
  "summary": null,
  "packageCount": 12,
  "organizerCount": 3,
  "startingPrice": 499,
  "priceMin": 499,
  "priceMax": 1699,
  "availableVariants": [
    "NIGHT_TREK",
    "FIREFLIES",
    "CAMPING",
    "TREK_ONLY"
  ],
  "filters": {
    "transportTypes": [
      "TRAIN",
      "NON_AC_BUS"
    ],
    "mealPlans": [
      "INCLUDED"
    ],
    "cities": [
      "MUMBAI"
    ],
    "variantTags": [
      "NIGHT_TREK",
      "FIREFLIES",
      "TREK_ONLY",
      "CAMPING"
    ],
    "organizers": [
      {
        "name": "Bhatakna",
        "slug": "bhatakna"
      },
      {
        "name": "Trekhievers",
        "slug": "trekhievers"
      },
      {
        "name": "Treks and Trails India",
        "slug": "treks-and-trails-india"
      }
    ]
  },
  "summaryTable": {
    "lowestPrice": 499,
    "cheapestOrganizerName": "Bhatakna",
    "cheapestOrganizerSlug": "bhatakna",
    "cheapestPackageTitle": "Fireflies & Clouds Special Kalsubai Night Trek 2026",
    "mealsSummary": [
      "Breakfast",
      "Lunch",
      "Tea and snacks",
      "Dinner"
    ],
    "organizerCount": 3,
    "variantCount": 5
  },
  "packages": [
    {
      "id": "cmpl30dof00uw1pnhopl1q75m",
      "title": "Fireflies & Clouds Special Kalsubai Night Trek 2026",
      "organizerName": "Bhatakna",
      "organizerSlug": "bhatakna",
      "trekName": "Kalsubai",
      "trekSlug": "kalsubai",
      "trekSummary": null,
      "sourceUrl": "https://www.bhatakna.com/tours/fireflies-clouds-special-kalsubai-night-trek",
      "priceInr": 499,
      "priceText": "₹499",
      "transportType": "TRAIN",
      "mealPlan": "INCLUDED",
      "forestFeeStatus": "INCLUDED",
      "listingCity": "MUMBAI",
      "variantTags": [
        "NIGHT_TREK",
        "FIREFLIES"
      ],
      "variantSignature": "NIGHT_TREK__FIREFLIES",
      "variantLabel": "Night trek + Fireflies",
      "mealsSummary": "Breakfast, Lunch",
      "staySummary": null,
      "inclusionHighlights": [
        "Breakfast, Lunch"
      ],
      "pickupLocations": [],
      "lastUpdatedAt": "2026-06-12T16:40:48.218Z",
      "updatedAtMs": 1781282448218,
      "searchText": "bhatakna fireflies & clouds special kalsubai night trek 2026 kalsubai night trek + fireflies mumbai breakfast, lunch breakfast, lunch"
    },
    {
      "id": "cmpe5sabm01gw8knh9i7fy94j",
      "title": "Kalsubai Night Trek",
      "organizerName": "Bhatakna",
      "organizerSlug": "bhatakna",
      "trekName": "Kalsubai",
      "trekSlug": "kalsubai",
      "trekSummary": null,
      "sourceUrl": "https://www.bhatakna.com/tours/kalsubai-night-trek",
      "priceInr": 499,
      "priceText": "₹499",
      "transportType": "TRAIN",
      "mealPlan": "INCLUDED",
      "forestFeeStatus": "INCLUDED",
      "listingCity": "MUMBAI",
      "variantTags": [
        "NIGHT_TREK"
      ],
      "variantSignature": "NIGHT_TREK",
      "variantLabel": "Night trek",
      "mealsSummary": "Breakfast, Lunch",
      "staySummary": null,
      "inclusionHighlights": [
        "Breakfast, Lunch"
      ],
      "pickupLocations": [],
      "lastUpdatedAt": "2026-06-12T16:42:04.850Z",
      "updatedAtMs": 1781282524850,
      "searchText": "bhatakna kalsubai night trek kalsubai night trek mumbai breakfast, lunch breakfast, lunch"
    },
    {
      "id": "cmpv555o705olg328h6d8qwab",
      "title": "Kalsubai Flag Hosting Trek",
      "organizerName": "Bhatakna",
      "organizerSlug": "bhatakna",
      "trekName": "Kalsubai",
      "trekSlug": "kalsubai",
      "trekSummary": null,
      "sourceUrl": "https://www.bhatakna.com/tours/kalsubai-flag-hosting-trek",
      "priceInr": 699,
      "priceText": "Rs. 699/- per person",
      "transportType": "NON_AC_BUS",
      "mealPlan": "INCLUDED",
      "forestFeeStatus": "INCLUDED",
      "listingCity": "MUMBAI",
      "variantTags": [
        "TREK_ONLY"
      ],
      "variantSignature": "TREK_ONLY",
      "variantLabel": "Trek",
      "mealsSummary": "Breakfast, Lunch",
      "staySummary": null,
      "inclusionHighlights": [
        "Breakfast, Lunch"
      ],
      "pickupLocations": [
        "Borivali",
        "Ghatkopar",
        "Thane",
        "Kalyan",
        "Chembur",
        "Sion",
        "Bari",
        "Bari Village"
      ],
      "lastUpdatedAt": "2026-06-12T16:42:02.931Z",
      "updatedAtMs": 1781282522931,
      "searchText": "bhatakna kalsubai flag hosting trek kalsubai trek mumbai breakfast, lunch breakfast, lunch borivali ghatkopar thane kalyan chembur sion bari bari village"
    },
    {
      "id": "cmpv55epa05qkg328zzsfmk30",
      "title": "Kalsubai Trek | Highest Peak of Maharashtra",
      "organizerName": "Bhatakna",
      "organizerSlug": "bhatakna",
      "trekName": "Kalsubai",
      "trekSlug": "kalsubai",
      "trekSummary": null,
      "sourceUrl": "https://www.bhatakna.com/tours/kalsubai-trek-highest-peak-of-maharashtra",
      "priceInr": 699,
      "priceText": "Rs. 699/- per person",
      "transportType": "NON_AC_BUS",
      "mealPlan": "INCLUDED",
      "forestFeeStatus": "INCLUDED",
      "listingCity": "MUMBAI",
      "variantTags": [
        "TREK_ONLY"
      ],
      "variantSignature": "TREK_ONLY",
      "variantLabel": "Trek",
      "mealsSummary": "Breakfast, Lunch",
      "staySummary": null,
      "inclusionHighlights": [
        "Breakfast, Lunch"
      ],
      "pickupLocations": [
        "Borivali",
        "Ghatkopar",
        "Thane",
        "Kalyan",
        "Chembur",
        "Sion",
        "Bari",
        "Bari Village"
      ],
      "lastUpdatedAt": "2026-06-12T16:42:12.486Z",
      "updatedAtMs": 1781282532486,
      "searchText": "bhatakna kalsubai trek | highest peak of maharashtra kalsubai trek mumbai breakfast, lunch breakfast, lunch borivali ghatkopar thane kalyan chembur sion bari bari village"
    },
    {
      "id": "cmpv4dlra01wzg328m6bfgkt4",
      "title": "Kalsubai Fireflies Special Trek",
      "organizerName": "Trekhievers",
      "organizerSlug": "trekhievers",
      "trekName": "Kalsubai",
      "trekSlug": "kalsubai",
      "trekSummary": null,
      "sourceUrl": "https://www.trekhievers.com/tours/kalsubai-fireflies-special-night-trek-125259",
      "priceInr": 699,
      "priceText": "₹699 per person",
      "transportType": "TRAIN",
      "mealPlan": "INCLUDED",
      "forestFeeStatus": "NOT_INCLUDED",
      "listingCity": "MUMBAI",
      "variantTags": [
        "FIREFLIES"
      ],
      "variantSignature": "FIREFLIES",
      "variantLabel": "Fireflies",
      "mealsSummary": "Breakfast, Lunch, Tea and snacks",
      "staySummary": null,
      "inclusionHighlights": [
        "Breakfast, Lunch, Tea and snacks"
      ],
      "pickupLocations": [],
      "lastUpdatedAt": "2026-06-12T16:22:50.025Z",
      "updatedAtMs": 1781281370025,
      "searchText": "trekhievers kalsubai fireflies special trek kalsubai fireflies mumbai breakfast, lunch, tea and snacks breakfast, lunch, tea and snacks"
    },
    {
      "id": "cmpe5r48f00088knh8ijwsq5t",
      "title": "Kalsubai Cloud Formation Trek | Mumbai",
      "organizerName": "Trekhievers",
      "organizerSlug": "trekhievers",
      "trekName": "Kalsubai",
      "trekSlug": "kalsubai",
      "trekSummary": null,
      "sourceUrl": "https://www.trekhievers.com/tours/kalsubai-trek",
      "priceInr": 699,
      "priceText": "₹699",
      "transportType": "TRAIN",
      "mealPlan": "INCLUDED",
      "forestFeeStatus": "INCLUDED",
      "listingCity": "MUMBAI",
      "variantTags": [
        "TREK_ONLY"
      ],
      "variantSignature": "TREK_ONLY",
      "variantLabel": "Trek",
      "mealsSummary": "Breakfast, Lunch, Tea and snacks",
      "staySummary": null,
      "inclusionHighlights": [
        "Breakfast, Lunch, Tea and snacks"
      ],
      "pickupLocations": [],
      "lastUpdatedAt": "2026-06-12T16:22:46.225Z",
      "updatedAtMs": 1781281366225,
      "searchText": "trekhievers kalsubai cloud formation trek | mumbai kalsubai trek mumbai breakfast, lunch, tea and snacks breakfast, lunch, tea and snacks"
    },
    {
      "id": "cmpv5msse09g3g3286akkr9qh",
      "title": "Kalsubai Monsoon Trek 2025",
      "organizerName": "Treks and Trails India",
      "organizerSlug": "treks-and-trails-india",
      "trekName": "Kalsubai",
      "trekSlug": "kalsubai",
      "trekSummary": null,
      "sourceUrl": "https://www.treksandtrails.org/tours/kalsubai-monsoon-trek-2025",
      "priceInr": 799,
      "priceText": "Rs. 799/- per person",
      "transportType": "TRAIN",
      "mealPlan": "INCLUDED",
      "forestFeeStatus": "NOT_INCLUDED",
      "listingCity": "MUMBAI",
      "variantTags": [
        "TREK_ONLY"
      ],
      "variantSignature": "TREK_ONLY",
      "variantLabel": "Trek",
      "mealsSummary": "Breakfast, Lunch",
      "staySummary": null,
      "inclusionHighlights": [
        "Breakfast, Lunch"
      ],
      "pickupLocations": [],
      "lastUpdatedAt": "2026-06-12T20:04:09.351Z",
      "updatedAtMs": 1781294649351,
      "searchText": "treks and trails india kalsubai monsoon trek 2025 kalsubai trek mumbai breakfast, lunch breakfast, lunch"
    },
    {
      "id": "cmpe5sc5d01i08knhf8z2qnof",
      "title": "Kalsubai Trekking & Camping",
      "organizerName": "Bhatakna",
      "organizerSlug": "bhatakna",
      "trekName": "Kalsubai",
      "trekSlug": "kalsubai",
      "trekSummary": null,
      "sourceUrl": "https://www.bhatakna.com/tours/kalsubai-camping",
      "priceInr": 999,
      "priceText": "₹999",
      "transportType": "TRAIN",
      "mealPlan": "INCLUDED",
      "forestFeeStatus": "INCLUDED",
      "listingCity": "MUMBAI",
      "variantTags": [
        "CAMPING"
      ],
      "variantSignature": "CAMPING",
      "variantLabel": "Camping",
      "mealsSummary": "Breakfast, Dinner, Tea and snacks",
      "staySummary": "Tent stay",
      "inclusionHighlights": [
        "Breakfast, Dinner, Tea and snacks",
        "Tent stay"
      ],
      "pickupLocations": [],
      "lastUpdatedAt": "2026-06-12T16:42:14.393Z",
      "updatedAtMs": 1781282534393,
      "searchText": "bhatakna kalsubai trekking & camping kalsubai camping mumbai breakfast, dinner, tea and snacks tent stay breakfast, dinner, tea and snacks tent stay"
    },
    {
      "id": "cmpv5tk540aucg3285p0szuv4",
      "title": "New Year Kalsubai Trek",
      "organizerName": "Treks and Trails India",
      "organizerSlug": "treks-and-trails-india",
      "trekName": "Kalsubai",
      "trekSlug": "kalsubai",
      "trekSummary": null,
      "sourceUrl": "https://www.treksandtrails.org/tours/new-year-night-trek-kalsubai-peak",
      "priceInr": 1099,
      "priceText": "Rs. 1099/- per person",
      "transportType": "TRAIN",
      "mealPlan": "INCLUDED",
      "forestFeeStatus": "UNKNOWN",
      "listingCity": "MUMBAI",
      "variantTags": [
        "TREK_ONLY"
      ],
      "variantSignature": "TREK_ONLY",
      "variantLabel": "Trek",
      "mealsSummary": "Breakfast, Lunch",
      "staySummary": "Hotel stay, Dormitory stay, Homestay",
      "inclusionHighlights": [
        "Breakfast, Lunch",
        "Hotel stay, Dormitory stay, Homestay"
      ],
      "pickupLocations": [],
      "lastUpdatedAt": "2026-06-12T20:08:37.014Z",
      "updatedAtMs": 1781294917014,
      "searchText": "treks and trails india new year kalsubai trek kalsubai trek mumbai breakfast, lunch hotel stay, dormitory stay, homestay breakfast, lunch hotel stay, dormitory stay, homestay"
    },
    {
      "id": "cmpe5reyi00j98knh2pz8plhi",
      "title": "Kalsubai Trek | AC Bus ₹1399 | Kasara Train ₹999",
      "organizerName": "Treks and Trails India",
      "organizerSlug": "treks-and-trails-india",
      "trekName": "Kalsubai",
      "trekSlug": "kalsubai",
      "trekSummary": null,
      "sourceUrl": "https://www.treksandtrails.org/tours/kalsubai-trek-highest-peak-of-maharashtra",
      "priceInr": 1399,
      "priceText": "₹1399",
      "transportType": "TRAIN",
      "mealPlan": "INCLUDED",
      "forestFeeStatus": "NOT_INCLUDED",
      "listingCity": "MUMBAI",
      "variantTags": [
        "TREK_ONLY"
      ],
      "variantSignature": "TREK_ONLY",
      "variantLabel": "Trek",
      "mealsSummary": "Breakfast, Lunch",
      "staySummary": null,
      "inclusionHighlights": [
        "Breakfast, Lunch"
      ],
      "pickupLocations": [],
      "lastUpdatedAt": "2026-06-12T20:04:15.541Z",
      "updatedAtMs": 1781294655541,
      "searchText": "treks and trails india kalsubai trek | ac bus ₹1399 | kasara train ₹999 kalsubai trek mumbai breakfast, lunch breakfast, lunch"
    },
    {
      "id": "cmpfjyf8m00ywuonh3legdenw",
      "title": "Kalsubai Camping from Kasara",
      "organizerName": "Treks and Trails India",
      "organizerSlug": "treks-and-trails-india",
      "trekName": "Kalsubai",
      "trekSlug": "kalsubai",
      "trekSummary": null,
      "sourceUrl": "https://www.treksandtrails.org/tours/kalsubai-peak-camping-and-trekking",
      "priceInr": 1599,
      "priceText": "Rs. 1599/- per person",
      "transportType": "TRAIN",
      "mealPlan": "INCLUDED",
      "forestFeeStatus": "UNKNOWN",
      "listingCity": "MUMBAI",
      "variantTags": [
        "CAMPING"
      ],
      "variantSignature": "CAMPING",
      "variantLabel": "Camping",
      "mealsSummary": "Breakfast, Dinner",
      "staySummary": "Tent stay, Homestay",
      "inclusionHighlights": [
        "Breakfast, Dinner",
        "Tent stay, Homestay"
      ],
      "pickupLocations": [],
      "lastUpdatedAt": "2026-06-12T20:04:07.414Z",
      "updatedAtMs": 1781294647414,
      "searchText": "treks and trails india kalsubai camping from kasara kalsubai camping mumbai breakfast, dinner tent stay, homestay breakfast, dinner tent stay, homestay"
    },
    {
      "id": "cmpv4dnnm01xhg328q5t96cg5",
      "title": "Kalsubai Trek & Camping | Mumbai",
      "organizerName": "Trekhievers",
      "organizerSlug": "trekhievers",
      "trekName": "Kalsubai",
      "trekSlug": "kalsubai",
      "trekSummary": null,
      "sourceUrl": "https://www.trekhievers.com/tours/kalsubai-trek-camping-mumbai-104911",
      "priceInr": 1699,
      "priceText": "₹1,699 per person",
      "transportType": "TRAIN",
      "mealPlan": "INCLUDED",
      "forestFeeStatus": "INCLUDED",
      "listingCity": "MUMBAI",
      "variantTags": [
        "CAMPING"
      ],
      "variantSignature": "CAMPING",
      "variantLabel": "Camping",
      "mealsSummary": "Breakfast, Dinner, Tea and snacks",
      "staySummary": "Tent stay",
      "inclusionHighlights": [
        "Breakfast, Dinner, Tea and snacks",
        "Tent stay"
      ],
      "pickupLocations": [],
      "lastUpdatedAt": "2026-06-12T16:22:51.924Z",
      "updatedAtMs": 1781281371924,
      "searchText": "trekhievers kalsubai trek & camping | mumbai kalsubai camping mumbai breakfast, dinner, tea and snacks tent stay breakfast, dinner, tea and snacks tent stay"
    }
  ],
  "updatedAt": "2026-06-12T20:08:37.014Z"
}
