{
  "name": "Blissful Himachal Kasol Tosh Manali",
  "slug": "blissful-himachal-kasol-tosh-manali",
  "region": null,
  "durationDays": null,
  "durationNights": null,
  "difficulty": "UNKNOWN",
  "summary": null,
  "packageCount": 1,
  "organizerCount": 1,
  "priceMin": 15999,
  "priceMax": 15999,
  "updatedAt": "2026-05-25T10:46:26.308Z",
  "filters": {
    "transportTypes": [
      "TRAIN"
    ],
    "mealPlans": [
      "INCLUDED"
    ],
    "cities": [
      "MIXED"
    ],
    "variantTags": [
      "TREK_ONLY"
    ],
    "organizers": [
      {
        "name": "Bhatakna",
        "slug": "bhatakna"
      }
    ]
  },
  "summaryTable": {
    "lowestPrice": 15999,
    "cheapestOrganizerName": "Bhatakna",
    "cheapestOrganizerSlug": "bhatakna",
    "cheapestPackageTitle": "Blissful Himachal - Kasol Tosh Manali",
    "mealsSummary": [
      "Breakfast",
      "Dinner"
    ],
    "organizerCount": 1,
    "variantCount": 1
  },
  "packages": [
    {
      "id": "cmpl2zrpg00fw1pnhfhs2a85m",
      "title": "Blissful Himachal - Kasol Tosh Manali",
      "organizerName": "Bhatakna",
      "organizerSlug": "bhatakna",
      "trekName": "Blissful Himachal Kasol Tosh Manali",
      "trekSlug": "blissful-himachal-kasol-tosh-manali",
      "trekSummary": null,
      "sourceUrl": "https://www.bhatakna.com/tours/kasol-tosh-manali",
      "priceInr": 15999,
      "priceText": "₹15,999",
      "transportType": "TRAIN",
      "mealPlan": "INCLUDED",
      "forestFeeStatus": "NOT_INCLUDED",
      "listingCity": "MIXED",
      "variantTags": [
        "TREK_ONLY"
      ],
      "variantSignature": "TREK_ONLY",
      "variantLabel": "Trek",
      "nextDepartureAt": null,
      "mealsSummary": "Breakfast, Dinner",
      "staySummary": "Hotel stay",
      "inclusionHighlights": [
        "Breakfast, Dinner",
        "Hotel stay"
      ],
      "pickupLocations": [],
      "lastUpdatedAt": "2026-05-25T10:46:26.308Z",
      "updatedAtMs": 1779705986308,
      "searchText": "bhatakna blissful himachal - kasol tosh manali blissful himachal kasol tosh manali trek mixed breakfast, dinner hotel stay breakfast, dinner hotel stay"
    }
  ]
}
