{
  "name": "Kalu Waterfall Trek God Valley Trek",
  "slug": "kalu-waterfall-trek-god-valley-trek",
  "region": "maharashtra",
  "durationDays": null,
  "durationNights": null,
  "difficulty": "UNKNOWN",
  "summary": null,
  "packageCount": 1,
  "organizerCount": 1,
  "priceMin": 699,
  "priceMax": 699,
  "updatedAt": "2026-07-02T15:39:09.652Z",
  "filters": {
    "transportTypes": [
      "AC_BUS"
    ],
    "mealPlans": [
      "INCLUDED"
    ],
    "cities": [
      "MUMBAI"
    ],
    "variantTags": [
      "TREK_ONLY"
    ],
    "organizers": [
      {
        "name": "Bhatakna",
        "slug": "bhatakna"
      }
    ]
  },
  "summaryTable": {
    "lowestPrice": 699,
    "cheapestOrganizerName": "Bhatakna",
    "cheapestOrganizerSlug": "bhatakna",
    "cheapestPackageTitle": "Kalu Waterfall Trek - God Valley Trek 2026",
    "mealsSummary": [
      "Breakfast",
      "Lunch",
      "Tea and snacks"
    ],
    "organizerCount": 1,
    "variantCount": 1
  },
  "packages": [
    {
      "id": "cmpv55icg05rkg328wjmuxqio",
      "title": "Kalu Waterfall Trek - God Valley Trek 2026",
      "organizerName": "Bhatakna",
      "organizerSlug": "bhatakna",
      "trekName": "Kalu Waterfall Trek God Valley Trek",
      "trekSlug": "kalu-waterfall-trek-god-valley-trek",
      "trekSummary": null,
      "sourceUrl": "https://www.bhatakna.com/tours/malshej-ghat-trek-and-kalu-waterfalls-trek",
      "priceInr": 699,
      "priceText": "Rs. 699/- per person",
      "transportType": "AC_BUS",
      "mealPlan": "INCLUDED",
      "forestFeeStatus": "NOT_INCLUDED",
      "listingCity": "MUMBAI",
      "variantTags": [
        "TREK_ONLY"
      ],
      "variantSignature": "TREK_ONLY",
      "variantLabel": "Trek",
      "mealsSummary": "Breakfast, Lunch, Tea and snacks",
      "staySummary": null,
      "inclusionHighlights": [
        "Breakfast, Lunch, Tea and snacks"
      ],
      "pickupLocations": [
        "Borivali",
        "Thane",
        "Kalyan",
        "Sion"
      ],
      "lastUpdatedAt": "2026-07-02T15:39:09.652Z",
      "updatedAtMs": 1783006749652,
      "searchText": "bhatakna kalu waterfall trek - god valley trek 2026 kalu waterfall trek god valley trek trek mumbai breakfast, lunch, tea and snacks breakfast, lunch, tea and snacks borivali thane kalyan sion"
    }
  ]
}
