{
  "name": "Torna Fort Trek",
  "slug": "torna-fort-trek",
  "region": null,
  "durationDays": null,
  "durationNights": null,
  "difficulty": "UNKNOWN",
  "summary": null,
  "packageCount": 1,
  "organizerCount": 1,
  "priceMin": 1700,
  "priceMax": 1700,
  "updatedAt": "2026-05-21T13:53:43.409Z",
  "filters": {
    "transportTypes": [
      "TRAIN"
    ],
    "mealPlans": [
      "INCLUDED"
    ],
    "cities": [],
    "organizers": [
      {
        "name": "Treks and Trails India",
        "slug": "treks-and-trails-india"
      }
    ]
  },
  "summaryTable": {
    "lowestPrice": 1700,
    "cheapestOrganizerName": "Treks and Trails India",
    "cheapestOrganizerSlug": "treks-and-trails-india",
    "cheapestPackageTitle": "Torna Fort Trek",
    "mealsSummary": [
      "Breakfast",
      "Lunch"
    ],
    "organizerCount": 1
  },
  "packages": [
    {
      "id": "cmpfjq29902e1v2nha57t1tet",
      "title": "Torna Fort Trek",
      "organizerName": "Treks and Trails India",
      "organizerSlug": "treks-and-trails-india",
      "trekName": "Torna Fort Trek",
      "trekSlug": "torna-fort-trek",
      "sourceUrl": "https://www.treksandtrails.org/tours/torna-fort-trek",
      "priceInr": 1700,
      "priceText": "Rs. 1700/- per person",
      "transportType": "TRAIN",
      "mealPlan": "INCLUDED",
      "forestFeeStatus": "UNKNOWN",
      "listingCity": "OTHER",
      "mealsSummary": "Breakfast, Lunch",
      "staySummary": "Tent stay",
      "inclusionHighlights": [
        "Breakfast, Lunch",
        "Tent stay"
      ],
      "pickupLocations": [],
      "lastUpdatedAt": "2026-05-21T13:53:43.409Z",
      "updatedAtMs": 1779371623409,
      "searchText": "treks and trails india torna fort trek torna fort trek other breakfast, lunch tent stay breakfast, lunch tent stay"
    }
  ]
}
